MANIFEST.in
README.rst
setup.py
docs/__init__.py
examples/__init__.py
examples/simple.py
flask_backstage/__init__.py
flask_backstage.egg-info/PKG-INFO
flask_backstage.egg-info/SOURCES.txt
flask_backstage.egg-info/dependency_links.txt
flask_backstage.egg-info/requires.txt
flask_backstage.egg-info/top_level.txt
flask_backstage/mongoengine/__init__.py
flask_backstage/mongoengine/admin/__init__.py
flask_backstage/mongoengine/admin/create_form.py
flask_backstage/mongoengine/admin/create_views.py
flask_backstage/mongoengine/admin/helps.py
flask_backstage/mongoengine/admin/widgets.py
flask_backstage/mongoengine/forms/__init__.py
flask_backstage/mongoengine/models/__init__.py
flask_backstage/mongoengine/static/favicon.ico
flask_backstage/mongoengine/static/css/AdminLTE.min.css
flask_backstage/mongoengine/static/css/backstage.css
flask_backstage/mongoengine/static/css/bootstrap.min.css
flask_backstage/mongoengine/static/css/pmd-select2.css
flask_backstage/mongoengine/static/css/readme
flask_backstage/mongoengine/static/css/select2-bootstrap.css
flask_backstage/mongoengine/static/css/select2.min.css
flask_backstage/mongoengine/static/css/skin-blue.min.css
flask_backstage/mongoengine/static/css/textfield.css
flask_backstage/mongoengine/static/css/typography.css
flask_backstage/mongoengine/static/error/css/err_style.css
flask_backstage/mongoengine/static/images/readme
flask_backstage/mongoengine/static/js/app.min.js
flask_backstage/mongoengine/static/js/bootstrap.min.js
flask_backstage/mongoengine/static/js/jquery-2.2.3.min.js
flask_backstage/mongoengine/static/js/pmd-select2.js
flask_backstage/mongoengine/static/js/readme
flask_backstage/mongoengine/static/js/select2.full.js
flask_backstage/mongoengine/static/js/textfield.js
flask_backstage/mongoengine/templates/admin/_macros.html
flask_backstage/mongoengine/templates/admin/create.html
flask_backstage/mongoengine/templates/admin/edit.html
flask_backstage/mongoengine/templates/admin/layout.html
flask_backstage/mongoengine/templates/admin/list.html
flask_backstage/mongoengine/templates/admin/login.html
flask_backstage/mongoengine/templates/admin/menu_add.html
flask_backstage/mongoengine/templates/admin/menu_edit.html
