Metadata-Version: 1.1
Name: flask-backstage
Version: 0.1.9
Summary: A backstage framework with very few code.
Home-page: https://github.com/huanglong123/flask-backstage
Author: pengwei
Author-email: 1300896173@qq.com
License: MIT
Platform: any
Classifier: Development Status :: 4 - Beta
Classifier: Environment :: Web Environment
Classifier: Intended Audience :: Developers
Classifier: License :: OSI Approved :: BSD License
Classifier: Operating System :: OS Independent
Classifier: Programming Language :: Python
Classifier: Topic :: Software Development :: Libraries :: Python Modules
Classifier: Programming Language :: Python :: 3.5
